CryEx/CryEx_diff.py
CryEx/CryEx_junctions.py
CryEx/CryEx_psi_calc.py
CryEx/CryEx_stringtie.py
CryEx/__init__.py
cryex_v2-2.0.2.dist-info/licenses/LICENSE
cryex_v2-2.0.2.dist-info/METADATA
cryex_v2-2.0.2.dist-info/WHEEL
cryex_v2-2.0.2.dist-info/entry_points.txt
cryex_v2-2.0.2.dist-info/top_level.txt
cryex_v2-2.0.2.dist-info/RECORD
