Metadata-Version: 2.4
Name: CryEx.v2
Version: 2.0.2
Summary: Cryptic Exon finder and splicing quantification
Home-page: https://github.com/giovanniquinones/CryEx
Author: Rong Zhen, Giovanni Quinones Valdez
Author-email: giovas@ucla.edu
Project-URL: Bug Tracker, https://github.com/giovanniquinones/CryEx/issues
Classifier: Programming Language :: Python :: 3
Classifier: License :: OSI Approved :: MIT License
Classifier: Operating System :: OS Independent
Requires-Python: >=3.8
License-File: LICENSE
Requires-Dist: multiprocess
Requires-Dist: numpy
Requires-Dist: pandas
Requires-Dist: pysam
Dynamic: license-file
